{
  "name": "users/rm1lyqky201zsuLoV7tB7ytRyoBL/masks/1753342315820_boywb/mask_pants.png",
  "bucket": "kapdaai-local.appspot.com",
  "metageneration": 1,
  "generation": 1753342316082,
  "contentType": "image/png",
  "storageClass": "STANDARD",
  "contentDisposition": "inline",
  "downloadTokens": [
    "0e02dc5e-77ad-4cd1-96fc-36ca44ca3bb7"
  ],
  "etag": "EqvrVtVg9BPJwsbfV1XgJn0v7n0",
  "customMetadata": {},
  "timeCreated": "2025-07-24T07:31:56.082Z",
  "updated": "2025-07-24T07:31:56.082Z",
  "size": 1201742,
  "md5Hash": "vsP3/ElkTV+5Lnm79VRL9g==",
  "crc32c": "1363480088"
}