{
  "name": "users/rm1lyqky201zsuLoV7tB7ytRyoBL/masks/1752393007745_mu/mask_shoes.png",
  "bucket": "kapdaai-local.appspot.com",
  "metageneration": 1,
  "generation": 1752393007959,
  "contentType": "image/png",
  "storageClass": "STANDARD",
  "contentDisposition": "inline",
  "downloadTokens": [
    "d90013e5-0584-4c89-93b4-c8e4c2e299ee"
  ],
  "etag": "tIesjWkFqdSowxeQOByX60fBfTE",
  "customMetadata": {},
  "timeCreated": "2025-07-13T07:50:07.959Z",
  "updated": "2025-07-13T07:50:07.959Z",
  "size": 960128,
  "md5Hash": "CXZyAC2hbryoXA2iz4xszA==",
  "crc32c": "583396287"
}